victron_ble_ha_parser/__init__.py
victron_ble_ha_parser/custom_state_data.py
victron_ble_ha_parser/parser.py
victron_ble_ha_parser-0.4.8.dist-info/licenses/LICENSE
victron_ble_ha_parser-0.4.8.dist-info/METADATA
victron_ble_ha_parser-0.4.8.dist-info/WHEEL
victron_ble_ha_parser-0.4.8.dist-info/top_level.txt
victron_ble_ha_parser-0.4.8.dist-info/RECORD
