Metadata-Version: 2.4
Name: victron_ble_ha_parser
Version: 0.4.8
Summary: A parser for Victron BLE messages suitable for use with Home Assistant
Author-email: Raj Laud <raj.laud@gmail.com>
License-Expression: Apache-2.0
License-File: LICENSE
Requires-Dist: bluetooth-sensor-state-data>=1.6.1
Requires-Dist: sensor-state-data>=2.16.0
Requires-Dist: victron-ble==0.9.2
Dynamic: license-file
